{
  "$schema": "demo-forge/project-analysis",
  "version": "1.0",
  "generated_at": "2026-02-24T10:30:00Z",
  "project": {
    "name": "cross-border-mall",
    "root": "/home/user/projects/cross-border-mall",
    "framework": {
      "language": "go",
      "web_framework": "gin",
      "orm": "gorm",
      "detected_by": [
        "go.mod: github.com/gin-gonic/gin",
        "go.mod: gorm.io/gorm"
      ]
    }
  },
  "models": [
    {
      "name": "Category",
      "source_file": "internal/model/category.go",
      "source_line": 8,
      "framework": "gorm",
      "table_name": "categories",
      "fields": [
        {
          "name": "ID",
          "json_name": "id",
          "type": "uint",
          "db_type": "bigint",
          "primary_key": true,
          "auto_increment": true,
          "nullable": false,
          "relation": null,
          "hints": []
        },
        {
          "name": "Name",
          "json_name": "name",
          "type": "string",
          "db_type": "varchar(50)",
          "primary_key": false,
          "auto_increment": false,
          "nullable": false,
          "relation": null,
          "hints": []
        },
        {
          "name": "IconURL",
          "json_name": "icon_url",
          "type": "string",
          "db_type": "varchar(500)",
          "primary_key": false,
          "auto_increment": false,
          "nullable": true,
          "relation": null,
          "hints": ["image_field"]
        },
        {
          "name": "SortOrder",
          "json_name": "sort_order",
          "type": "int",
          "db_type": "int",
          "primary_key": false,
          "auto_increment": false,
          "nullable": false,
          "relation": null,
          "hints": []
        }
      ],
      "relations_summary": [
        { "type": "has_many", "target": "Product", "via": "CategoryID" }
      ]
    },
    {
      "name": "Product",
      "source_file": "internal/model/product.go",
      "source_line": 10,
      "framework": "gorm",
      "table_name": "products",
      "fields": [
        {
          "name": "ID",
          "json_name": "id",
          "type": "uint",
          "db_type": "bigint",
          "primary_key": true,
          "auto_increment": true,
          "nullable": false,
          "relation": null,
          "hints": []
        },
        {
          "name": "Name",
          "json_name": "name",
          "type": "string",
          "db_type": "varchar(200)",
          "primary_key": false,
          "auto_increment": false,
          "nullable": false,
          "relation": null,
          "hints": []
        },
        {
          "name": "Description",
          "json_name": "description",
          "type": "string",
          "db_type": "text",
          "primary_key": false,
          "auto_increment": false,
          "nullable": true,
          "relation": null,
          "hints": []
        },
        {
          "name": "Price",
          "json_name": "price",
          "type": "float64",
          "db_type": "decimal(10,2)",
          "primary_key": false,
          "auto_increment": false,
          "nullable": false,
          "relation": null,
          "hints": []
        },
        {
          "name": "ImageURL",
          "json_name": "image_url",
          "type": "string",
          "db_type": "varchar(500)",
          "primary_key": false,
          "auto_increment": false,
          "nullable": true,
          "relation": null,
          "hints": ["image_field"]
        },
        {
          "name": "Stock",
          "json_name": "stock",
          "type": "int",
          "db_type": "int",
          "primary_key": false,
          "auto_increment": false,
          "nullable": false,
          "relation": null,
          "hints": []
        },
        {
          "name": "CategoryID",
          "json_name": "category_id",
          "type": "uint",
          "db_type": "bigint",
          "primary_key": false,
          "auto_increment": false,
          "nullable": false,
          "relation": {
            "type": "belongs_to",
            "model": "Category",
            "foreign_key": "CategoryID",
            "references": "ID"
          },
          "hints": []
        },
        {
          "name": "Status",
          "json_name": "status",
          "type": "string",
          "db_type": "varchar(20)",
          "primary_key": false,
          "auto_increment": false,
          "nullable": false,
          "relation": null,
          "hints": []
        }
      ],
      "relations_summary": [
        { "type": "belongs_to", "target": "Category", "via": "CategoryID" }
      ]
    },
    {
      "name": "User",
      "source_file": "internal/model/user.go",
      "source_line": 12,
      "framework": "gorm",
      "table_name": "users",
      "fields": [
        {
          "name": "ID",
          "json_name": "id",
          "type": "uint",
          "db_type": "bigint",
          "primary_key": true,
          "auto_increment": true,
          "nullable": false,
          "relation": null,
          "hints": []
        },
        {
          "name": "Username",
          "json_name": "username",
          "type": "string",
          "db_type": "varchar(50)",
          "primary_key": false,
          "auto_increment": false,
          "nullable": false,
          "relation": null,
          "hints": []
        },
        {
          "name": "Email",
          "json_name": "email",
          "type": "string",
          "db_type": "varchar(100)",
          "primary_key": false,
          "auto_increment": false,
          "nullable": false,
          "relation": null,
          "hints": []
        },
        {
          "name": "Avatar",
          "json_name": "avatar",
          "type": "string",
          "db_type": "varchar(500)",
          "primary_key": false,
          "auto_increment": false,
          "nullable": true,
          "relation": null,
          "hints": ["image_field"]
        },
        {
          "name": "Role",
          "json_name": "role",
          "type": "string",
          "db_type": "varchar(20)",
          "primary_key": false,
          "auto_increment": false,
          "nullable": false,
          "relation": null,
          "hints": []
        }
      ],
      "relations_summary": [
        { "type": "has_many", "target": "Order", "via": "UserID" }
      ]
    },
    {
      "name": "Order",
      "source_file": "internal/model/order.go",
      "source_line": 10,
      "framework": "gorm",
      "table_name": "orders",
      "fields": [
        {
          "name": "ID",
          "json_name": "id",
          "type": "uint",
          "db_type": "bigint",
          "primary_key": true,
          "auto_increment": true,
          "nullable": false,
          "relation": null,
          "hints": []
        },
        {
          "name": "OrderNo",
          "json_name": "order_no",
          "type": "string",
          "db_type": "varchar(32)",
          "primary_key": false,
          "auto_increment": false,
          "nullable": false,
          "relation": null,
          "hints": []
        },
        {
          "name": "UserID",
          "json_name": "user_id",
          "type": "uint",
          "db_type": "bigint",
          "primary_key": false,
          "auto_increment": false,
          "nullable": false,
          "relation": {
            "type": "belongs_to",
            "model": "User",
            "foreign_key": "UserID",
            "references": "ID"
          },
          "hints": []
        },
        {
          "name": "TotalAmount",
          "json_name": "total_amount",
          "type": "float64",
          "db_type": "decimal(10,2)",
          "primary_key": false,
          "auto_increment": false,
          "nullable": false,
          "relation": null,
          "hints": []
        },
        {
          "name": "Status",
          "json_name": "status",
          "type": "string",
          "db_type": "varchar(20)",
          "primary_key": false,
          "auto_increment": false,
          "nullable": false,
          "relation": null,
          "hints": []
        },
        {
          "name": "ShippingAddress",
          "json_name": "shipping_address",
          "type": "string",
          "db_type": "varchar(300)",
          "primary_key": false,
          "auto_increment": false,
          "nullable": false,
          "relation": null,
          "hints": []
        }
      ],
      "relations_summary": [
        { "type": "belongs_to", "target": "User", "via": "UserID" }
      ]
    }
  ],
  "endpoints": [
    {
      "method": "POST",
      "path": "/api/v1/auth/login",
      "handler": "Login",
      "source_file": "internal/handler/auth.go",
      "source_line": 28,
      "param_struct": "LoginRequest",
      "param_fields": [
        { "name": "username", "type": "string", "required": true },
        { "name": "password", "type": "string", "required": true }
      ],
      "is_upload": false,
      "auth_required": false,
      "tags": ["auth", "login"]
    },
    {
      "method": "POST",
      "path": "/api/v1/categories",
      "handler": "CreateCategory",
      "source_file": "internal/handler/category.go",
      "source_line": 30,
      "param_struct": "CreateCategoryRequest",
      "param_fields": [
        { "name": "name", "type": "string", "required": true },
        { "name": "icon_url", "type": "string", "required": false },
        { "name": "sort_order", "type": "int", "required": false }
      ],
      "is_upload": false,
      "auth_required": true,
      "tags": ["create", "category"]
    },
    {
      "method": "GET",
      "path": "/api/v1/categories",
      "handler": "ListCategories",
      "source_file": "internal/handler/category.go",
      "source_line": 10,
      "param_struct": null,
      "param_fields": [],
      "is_upload": false,
      "auth_required": true,
      "tags": ["list", "category"]
    },
    {
      "method": "DELETE",
      "path": "/api/v1/categories/:id",
      "handler": "DeleteCategory",
      "source_file": "internal/handler/category.go",
      "source_line": 65,
      "param_struct": null,
      "param_fields": [
        { "name": "id", "type": "uint", "required": true, "in": "path" }
      ],
      "is_upload": false,
      "auth_required": true,
      "tags": ["delete", "category"]
    },
    {
      "method": "POST",
      "path": "/api/v1/products",
      "handler": "CreateProduct",
      "source_file": "internal/handler/product.go",
      "source_line": 42,
      "param_struct": "CreateProductRequest",
      "param_fields": [
        { "name": "name", "type": "string", "required": true },
        { "name": "price", "type": "float64", "required": true },
        { "name": "description", "type": "string", "required": false },
        { "name": "category_id", "type": "uint", "required": true },
        { "name": "image_url", "type": "string", "required": false },
        { "name": "stock", "type": "int", "required": true }
      ],
      "is_upload": false,
      "auth_required": true,
      "tags": ["create", "product"]
    },
    {
      "method": "GET",
      "path": "/api/v1/products",
      "handler": "ListProducts",
      "source_file": "internal/handler/product.go",
      "source_line": 12,
      "param_struct": null,
      "param_fields": [
        { "name": "page", "type": "int", "required": false, "in": "query" },
        { "name": "size", "type": "int", "required": false, "in": "query" },
        { "name": "category_id", "type": "uint", "required": false, "in": "query" }
      ],
      "is_upload": false,
      "auth_required": true,
      "tags": ["list", "product"]
    },
    {
      "method": "PUT",
      "path": "/api/v1/products/:id",
      "handler": "UpdateProduct",
      "source_file": "internal/handler/product.go",
      "source_line": 70,
      "param_struct": "UpdateProductRequest",
      "param_fields": [
        { "name": "name", "type": "string", "required": false },
        { "name": "price", "type": "float64", "required": false },
        { "name": "description", "type": "string", "required": false },
        { "name": "image_url", "type": "string", "required": false },
        { "name": "stock", "type": "int", "required": false }
      ],
      "is_upload": false,
      "auth_required": true,
      "tags": ["update", "product"]
    },
    {
      "method": "DELETE",
      "path": "/api/v1/products/:id",
      "handler": "DeleteProduct",
      "source_file": "internal/handler/product.go",
      "source_line": 98,
      "param_struct": null,
      "param_fields": [
        { "name": "id", "type": "uint", "required": true, "in": "path" }
      ],
      "is_upload": false,
      "auth_required": true,
      "tags": ["delete", "product"]
    },
    {
      "method": "POST",
      "path": "/api/v1/users",
      "handler": "CreateUser",
      "source_file": "internal/handler/user.go",
      "source_line": 35,
      "param_struct": "CreateUserRequest",
      "param_fields": [
        { "name": "username", "type": "string", "required": true },
        { "name": "email", "type": "string", "required": true },
        { "name": "password", "type": "string", "required": true },
        { "name": "role", "type": "string", "required": false }
      ],
      "is_upload": false,
      "auth_required": true,
      "tags": ["create", "user"]
    },
    {
      "method": "GET",
      "path": "/api/v1/users",
      "handler": "ListUsers",
      "source_file": "internal/handler/user.go",
      "source_line": 12,
      "param_struct": null,
      "param_fields": [],
      "is_upload": false,
      "auth_required": true,
      "tags": ["list", "user"]
    },
    {
      "method": "DELETE",
      "path": "/api/v1/users/:id",
      "handler": "DeleteUser",
      "source_file": "internal/handler/user.go",
      "source_line": 88,
      "param_struct": null,
      "param_fields": [
        { "name": "id", "type": "uint", "required": true, "in": "path" }
      ],
      "is_upload": false,
      "auth_required": true,
      "tags": ["delete", "user"]
    },
    {
      "method": "POST",
      "path": "/api/v1/orders",
      "handler": "CreateOrder",
      "source_file": "internal/handler/order.go",
      "source_line": 30,
      "param_struct": "CreateOrderRequest",
      "param_fields": [
        {
          "name": "items",
          "type": "array",
          "required": true,
          "item_fields": [
            { "name": "product_id", "type": "uint", "required": true },
            { "name": "quantity", "type": "int", "required": true }
          ]
        },
        { "name": "shipping_address", "type": "string", "required": true }
      ],
      "is_upload": false,
      "auth_required": true,
      "tags": ["create", "order"]
    },
    {
      "method": "GET",
      "path": "/api/v1/orders",
      "handler": "ListOrders",
      "source_file": "internal/handler/order.go",
      "source_line": 12,
      "param_struct": null,
      "param_fields": [],
      "is_upload": false,
      "auth_required": true,
      "tags": ["list", "order"]
    },
    {
      "method": "POST",
      "path": "/api/v1/upload/image",
      "handler": "UploadImage",
      "source_file": "internal/handler/upload.go",
      "source_line": 15,
      "param_struct": null,
      "param_fields": [
        { "name": "file", "type": "multipart/file", "required": true }
      ],
      "is_upload": true,
      "auth_required": true,
      "tags": ["upload", "image"]
    }
  ],
  "model_api_mapping": [
    {
      "model": "Category",
      "match_confidence": "high",
      "match_method": ["name_similarity", "param_matching"],
      "apis": {
        "create": { "method": "POST", "path": "/api/v1/categories" },
        "list": { "method": "GET", "path": "/api/v1/categories" },
        "get": null,
        "update": null,
        "delete": { "method": "DELETE", "path": "/api/v1/categories/:id" }
      },
      "has_upload": false,
      "upload_via": "/api/v1/upload/image",
      "image_fields": ["icon_url"]
    },
    {
      "model": "Product",
      "match_confidence": "high",
      "match_method": ["name_similarity", "param_matching"],
      "apis": {
        "create": { "method": "POST", "path": "/api/v1/products" },
        "list": { "method": "GET", "path": "/api/v1/products" },
        "get": null,
        "update": { "method": "PUT", "path": "/api/v1/products/:id" },
        "delete": { "method": "DELETE", "path": "/api/v1/products/:id" }
      },
      "has_upload": false,
      "upload_via": "/api/v1/upload/image",
      "image_fields": ["image_url"]
    },
    {
      "model": "User",
      "match_confidence": "high",
      "match_method": ["name_similarity", "param_matching"],
      "apis": {
        "create": { "method": "POST", "path": "/api/v1/users" },
        "list": { "method": "GET", "path": "/api/v1/users" },
        "get": null,
        "update": null,
        "delete": { "method": "DELETE", "path": "/api/v1/users/:id" }
      },
      "has_upload": false,
      "upload_via": "/api/v1/upload/image",
      "image_fields": ["avatar"]
    },
    {
      "model": "Order",
      "match_confidence": "high",
      "match_method": ["name_similarity", "param_matching"],
      "apis": {
        "create": { "method": "POST", "path": "/api/v1/orders" },
        "list": { "method": "GET", "path": "/api/v1/orders" },
        "get": null,
        "update": null,
        "delete": null
      },
      "has_upload": false,
      "upload_via": null,
      "image_fields": []
    }
  ],
  "auth": {
    "login_endpoint": {
      "method": "POST",
      "path": "/api/v1/auth/login"
    },
    "token_type": "bearer",
    "token_location": "response.data.token",
    "header_format": "Authorization: Bearer {token}"
  },
  "upload": {
    "endpoints": [
      {
        "method": "POST",
        "path": "/api/v1/upload/image",
        "file_param": "file",
        "response_url_field": "data.url",
        "accepted_types": ["image/jpeg", "image/png", "image/webp"]
      }
    ]
  },
  "user_confirmed": false,
  "user_corrections": []
}
